webmix/__init__.py
webmix/web_utils.py
webmix-0.0.10.dist-info/METADATA
webmix-0.0.10.dist-info/WHEEL
webmix-0.0.10.dist-info/top_level.txt
webmix-0.0.10.dist-info/RECORD
