Metadata-Version: 2.1
Name: webmix
Version: 0.0.10
Summary: A set of utilities for web scraping and automation, supporting multiple backends: requests, urllib, and selenium.
Home-page: https://github.com/ng-fukgin/webmix
Author: wfj
Author-email: wfj.0000@gmail.com
License: MIT
Project-URL: Bug Tracker, https://github.com/ng-fukgin/webmix/issues
Project-URL: Documentation, https://github.com/ng-fukgin/webmix/wiki
Project-URL: Source Code, https://github.com/ng-fukgin/webmix
Keywords: webmix,网页抓取,自动化,requests,urllib,selenium,web scraping,automation
Platform: any
Classifier: Development Status :: 3 - Alpha
Classifier: Intended Audience :: Developers
Classifier: License :: OSI Approved :: MIT License
Classifier: Programming Language :: Python
Classifier: Programming Language :: Python :: 3
Classifier: Programming Language :: Python :: 3.6
Classifier: Programming Language :: Python :: 3.7
Classifier: Programming Language :: Python :: 3.8
Classifier: Programming Language :: Python :: 3.9
Classifier: Operating System :: OS Independent
Requires-Python: >=3.7
Requires-Dist: requests (<=3.0.0,>=2.0.0)
Requires-Dist: selenium (==3.141.0)
Requires-Dist: webdriver-manager (<=2.0.0,>=1.0.0)
Requires-Dist: aiohttp (<=4.0.0,>=3.0.0)
Requires-Dist: asyncio (<=4.0.0,>=3.0.0)
